README.rst
setup.py
wrappers/__init__.py
wrappers/_ssl.py
wrappers/clock.py
wrappers/logger.py
wrappers/pq.py
wrappers/storage.py
wrappers/utils.py
wrappers.egg-info/PKG-INFO
wrappers.egg-info/SOURCES.txt
wrappers.egg-info/dependency_links.txt
wrappers.egg-info/top_level.txt