Metadata-Version: 1.1
Name: wrappers
Version: 0.1.8
Summary: convenient wrappers around existing modules
Home-page: https://github.com/comsul/wrappers
Author: comsul
Author-email: chnrxn+pypi@gmail.com
License: UNKNOWN
Platform: UNKNOWN
Classifier: Development Status :: 3 - Alpha
